oci_langgraph/__init__.py
oci_langgraph/agent_base.py
oci_langgraph/oci_queue_base.py
oci_langgraph/oci_queue_listener.py
oci_langgraph/oci_queue_publisher.py
oci_langgraph/oracle_apm_transport.py
oci_langgraph/oracle_checkpoint_saver.py
oci_langgraph/utils.py
oci_langgraph-0.1.9.dist-info/licenses/LICENSE
oci_langgraph-0.1.9.dist-info/METADATA
oci_langgraph-0.1.9.dist-info/WHEEL
oci_langgraph-0.1.9.dist-info/top_level.txt
oci_langgraph-0.1.9.dist-info/RECORD
