Metadata-Version: 2.4
Name: oci_langgraph
Version: 0.1.9
Summary: A set of utility classes to enhance AI agent development with LangGraph and OCI
Home-page: https://github.com/luigisaetta/oci_langgraph
Author: L. Saetta
Author-email: "L. Saetta" <luigi.saetta@gmail.com>
License: MIT
Classifier: Programming Language :: Python :: 3
Classifier: License :: OSI Approved :: MIT License
Classifier: Operating System :: OS Independent
Classifier: Development Status :: 3 - Alpha
Classifier: Intended Audience :: Developers
Classifier: Topic :: Software Development :: Libraries :: Python Modules
Requires-Python: >=3.11
License-File: LICENSE
Requires-Dist: langchain>=0.3.24
Requires-Dist: langchain-community>=0.3.23
Requires-Dist: langgraph>=0.4.1
Requires-Dist: oci>=2.150.3
Requires-Dist: oracledb>=3.1.0
Requires-Dist: py-zipkin==1.2.8
Dynamic: license-file
